rpamaker/RPA.py
rpamaker/__init__.py
rpamaker/listener.py
rpamaker/orquestador.py
rpamaker/utils.py
rpamaker/workspace_api.py
rpamaker-0.0.42.dist-info/METADATA
rpamaker-0.0.42.dist-info/WHEEL
rpamaker-0.0.42.dist-info/top_level.txt
rpamaker-0.0.42.dist-info/RECORD
