Metadata-Version: 2.1
Name: rpamaker
Version: 0.0.42
Summary: RPAMAKER - Tools for RPA
Author: RPAMAKER
Author-email: <andres@rpamaker.com>
Keywords: python,rpa,robotframework,rpamaker
Classifier: Development Status :: 1 - Planning
Classifier: Intended Audience :: Developers
Classifier: Programming Language :: Python :: 3
Classifier: Operating System :: Unix
Classifier: Operating System :: MacOS :: MacOS X
Classifier: Operating System :: Microsoft :: Windows
Requires-Dist: python-decouple
Requires-Dist: fastapi
Requires-Dist: uvicorn
Requires-Dist: requests
Requires-Dist: python-dotenv
